pycronserver/__init__.py
pycronserver/__main__.py
pycronserver/_version.py
pycronserver/local.py
pycronserver/server.py
pycronserver-0.0.1.dist-info/LICENSE
pycronserver-0.0.1.dist-info/METADATA
pycronserver-0.0.1.dist-info/WHEEL
pycronserver-0.0.1.dist-info/entry_points.txt
pycronserver-0.0.1.dist-info/top_level.txt
pycronserver-0.0.1.dist-info/RECORD
