Metadata-Version: 2.1
Name: pycronserver
Version: 0.0.1
Summary: Cron server for python functions
Home-page: https://github.com/pyscioffice/pycronserver
Author: Jan Janssen
Author-email: jan.janssen@outlook.com
License: BSD
Platform: UNKNOWN
License-File: LICENSE
Requires-Dist: sqlalchemy (>=1.4.31)
Requires-Dist: python-crontab (>=2.5.1)
